README.md
setup.py
easytext/__init__.py
easytext/__main__.py
easytext/algorithms.py
easytext/docmodel.py
easytext/easytext.py
easytext/fileio.py
easytext/glovetools.py
easytext/grammar.py
easytext/pipelines.py
easytext/reports.py
easytext/subcommand_functions.py
easytext.egg-info/PKG-INFO
easytext.egg-info/SOURCES.txt
easytext.egg-info/dependency_links.txt
easytext.egg-info/not-zip-safe
easytext.egg-info/requires.txt
easytext.egg-info/top_level.txt