Metadata-Version: 1.1
Name: easytext
Version: 0.1
Summary: Simple text analysis tools with command line interface that writes to excel files.
Home-page: https://github.com/devincornell/easytext
Author: Devin J. Cornell
Author-email: devinj.cornell@gmail.com
License: MIT
Download-URL: https://github.com/devincornell/easytext/archive/v0.1.tar.gz
Keywords: text analysis,topic modeling,parse trees,educational
Platform: UNKNOWN
